osbot_playwright/__init__.py
osbot_playwright/_extra_methdos_osbot.py
osbot_playwright/docker/Build__Docker_Playwright.py
osbot_playwright/docker/ECR__Docker_Playwright.py
osbot_playwright/docker/Lambda__Docker_Playwright.py
osbot_playwright/docker/Local__Docker_Playwright.py
osbot_playwright/docker/__iniit__.py
osbot_playwright/docker/images/osbot_playwright/dockerfile
osbot_playwright/docker/images/osbot_playwright/handler.py
osbot_playwright/docker/images/osbot_playwright/requirements.txt
osbot_playwright/docker/images/osbot_playwright/run-docker.sh
osbot_playwright/html_parser/Html_Parser.py
osbot_playwright/html_parser/__init__.py
osbot_playwright/playwright/__init__.py
osbot_playwright/playwright/api/API_Browserless.py
osbot_playwright/playwright/api/Playwright_Browser.py
osbot_playwright/playwright/api/Playwright_Browser__Chrome.py
osbot_playwright/playwright/api/Playwright_CLI.py
osbot_playwright/playwright/api/Playwright_Install.py
osbot_playwright/playwright/api/Playwright_Page.py
osbot_playwright/playwright/api/Playwright_Process.py
osbot_playwright/playwright/api/Playwright_Requests.py
osbot_playwright/playwright/api/__init__.py
osbot_playwright/playwright/fastapi/Fast_API_Playwright.py
osbot_playwright/playwright/fastapi/Routes__Playwright.py
osbot_playwright/playwright/fastapi/__init__.py
osbot_playwright/version
osbot_playwright-0.6.10.dist-info/LICENSE
osbot_playwright-0.6.10.dist-info/METADATA
osbot_playwright-0.6.10.dist-info/WHEEL
osbot_playwright-0.6.10.dist-info/RECORD
